nops_sdk/_settings/__init__.py
nops_sdk/_settings/settings.py
nops_sdk/account/__init__.py
nops_sdk/account/account.py
nops_sdk/api/__init__.py
nops_sdk/api/_api_request.py
nops_sdk/api/_boto_session.py
nops_sdk/api/_decorators.py
nops_sdk/api/api_client.py
nops_sdk/client/__init__.py
nops_sdk/client/client.py
nops_sdk/cloud_infrastructure/__init__.py
nops_sdk/cloud_infrastructure/_cloud_operation_group.py
nops_sdk/cloud_infrastructure/_resource.py
nops_sdk/cloud_infrastructure/ami.py
nops_sdk/cloud_infrastructure/cloud_operation.py
nops_sdk/cloud_infrastructure/eks_cluster.py
nops_sdk/cloud_infrastructure/enums.py
nops_sdk/cloud_infrastructure/instance.py
nops_sdk/cloud_infrastructure/rds_instance.py
nops_sdk/cloud_infrastructure/security_group.py
nops_sdk/cloud_infrastructure/subnet.py
nops_sdk/cloud_infrastructure/vpc.py
nops_sdk/exceptions/__init__.py
nops_sdk/exceptions/exceptions.py
nops_sdk/graphql/__init__.py
nops_sdk/graphql/graphql.py
nops_sdk/k8s/__init__.py
nops_sdk/k8s/pod_recommendations.py
nops_sdk/pkg_version.py
nops_sdk/pricing/__init__.py
nops_sdk/pricing/pricing.py
nops_sdk/ri/__init__.py
nops_sdk/ri/query.py
nops_sdk/ri/ri_utilization.py
nops_sdk/ri/schemas.py
nops_sdk-0.7.3.dist-info/WHEEL
nops_sdk-0.7.3.dist-info/METADATA
nops_sdk-0.7.3.dist-info/RECORD
