Metadata-Version: 2.1
Name: nops-sdk
Version: 0.7.3
Summary: SDK for the nOps API
Author: nOps Engineers
Author-email: eng@nops.io
Requires-Python: >=3.9,<4.0
Classifier: Programming Language :: Python :: 3
Classifier: Programming Language :: Python :: 3.9
Classifier: Programming Language :: Python :: 3.10
Classifier: Programming Language :: Python :: 3.11
Requires-Dist: boto3 (>=1.21.42,<2.0.0)
Requires-Dist: isort (>=5.10.1,<6.0.0)
Requires-Dist: pyflakes (>=2.4.0,<3.0.0)
Requires-Dist: pytest (>=7.1.1,<8.0.0)
Requires-Dist: requests (>=2.27.1,<3.0.0)
